tomopyui/__init__.py
tomopyui/_sharedvars.py
tomopyui/_version.py
tomopyui/backend/__init__.py
tomopyui/backend/align.py
tomopyui/backend/io.py
tomopyui/backend/recon.py
tomopyui/backend/runanalysis.py
tomopyui/backend/util/__init__.py
tomopyui/backend/util/center.py
tomopyui/backend/util/dask_downsample.py
tomopyui/backend/util/padding.py
tomopyui/backend/util/dxchange/__init__.py
tomopyui/backend/util/dxchange/reader.py
tomopyui/backend/util/registration/__init__.py
tomopyui/backend/util/registration/_masked_phase_cross_correlation_cupy.py
tomopyui/backend/util/registration/_phase_cross_correlation_cucim.py
tomopyui/backend/util/registration/_phase_cross_correlation_cupy.py
tomopyui/backend/util/registration/fft.py
tomopyui/backend/util/registration/fft_cucim.py
tomopyui/tomocupy/__init__.py
tomopyui/tomocupy/prep/__init__.py
tomopyui/tomocupy/prep/alignment.py
tomopyui/tomocupy/prep/sampling.py
tomopyui/tomocupy/recon/__init__.py
tomopyui/tomocupy/recon/algorithm.py
tomopyui/widgets/__init__.py
tomopyui/widgets/analysis.py
tomopyui/widgets/center.py
tomopyui/widgets/dataexplorer.py
tomopyui/widgets/helpers.py
tomopyui/widgets/imports.py
tomopyui/widgets/main.py
tomopyui/widgets/prep.py
tomopyui/widgets/view.py
tomopyui-0.1.0.dist-info/LICENSE
tomopyui-0.1.0.dist-info/METADATA
tomopyui-0.1.0.dist-info/WHEEL
tomopyui-0.1.0.dist-info/top_level.txt
tomopyui-0.1.0.dist-info/RECORD
