Metadata-Version: 2.1
Name: tomopyui
Version: 0.1.0
Summary: A graphical user interface for tomopy.
Home-page: https://github.com/samwelborn/tomopyui
Author: Samuel Scott Welborn
Author-email: swelborn@seas.upenn.edu
License: BSD license
Project-URL: Source Code, https://github.com/samwelborn/tomopyui
Platform: UNKNOWN
Classifier: License :: OSI Approved :: BSD License
Classifier: Natural Language :: English
Classifier: Operating System :: OS Independent
Classifier: Programming Language :: Python :: 3
Classifier: Programming Language :: Python :: 3.9
Requires-Python: >=3.7
License-File: LICENSE
